bonnibel/__init__.py
bonnibel/build_context.py
bonnibel/module.py
bonnibel/project.py
bonnibel/rules.ninja
bonnibel/source.py
bonnibel/version.py
bonnibel-3.0.2.data/scripts/pb
bonnibel-3.0.2.dist-info/METADATA
bonnibel-3.0.2.dist-info/WHEEL
bonnibel-3.0.2.dist-info/top_level.txt
bonnibel-3.0.2.dist-info/RECORD
