Metadata-Version: 2.1
Name: bonnibel
Version: 3.0.2
Summary: Build script generator for the jsix operating system
Home-page: https://github.com/justinian/bonnibel
Author: Justin C. Miller
Author-email: justin@justin.cm
License: MIT
Keywords: build,ninja,generator
Platform: UNKNOWN
Requires-Dist: click
Requires-Dist: ninja
Requires-Dist: toml
